xrtpy/__init__.py
xrtpy/version.py
xrtpy/data/README.rst
xrtpy/data/channels/xrt_contam_on_ccd.geny
xrtpy/data/channels/xrt_contam_on_filter.geny
xrtpy/image_correction/__init__.py
xrtpy/image_correction/deconvolve.py
xrtpy/image_correction/remove_lightleak.py
xrtpy/image_correction/data/example_data/comp_XRT20150621_055911.7.fits
xrtpy/response/__init__.py
xrtpy/response/channel.py
xrtpy/response/effective_area.py
xrtpy/response/temperature_from_filter_ratio.py
xrtpy/response/temperature_response.py
xrtpy/response/data/.gitignore
xrtpy/response/data/XRT_emiss_model.default_CHIANTI.geny
xrtpy/response/data/n_DEHP.txt
xrtpy/response/data/xrt_channels_v0017.genx
xrtpy/response/data/xrt_contam_on_ccd.geny
xrtpy/response/data/xrt_contam_on_filter.geny
xrtpy/response/data/chianti_emission_models/XRT_emiss_model.default_CHIANTI.geny
xrtpy/response/data/chianti_emission_models/XRT_emiss_model.default_CHIANTI_hybrid.geny
xrtpy/response/data/chianti_emission_models/XRT_emiss_model.default_CHIANTI_photospheric.geny
xrtpy/util/__init__.py
xrtpy/util/filename2repo_path.py
xrtpy/util/make_exposure_map.py
xrtpy/util/time.py
xrtpy-0.5.0.dist-info/licenses/LICENSE
xrtpy-0.5.0.dist-info/METADATA
xrtpy-0.5.0.dist-info/WHEEL
xrtpy-0.5.0.dist-info/top_level.txt
xrtpy-0.5.0.dist-info/RECORD
