Metadata-Version: 2.4
Name: xrtpy
Version: 0.5.0
Summary: For analyzing data from the X-Ray Telescope (XRT) on the Hinode spacecraft.
Author: Will Barnes, Stuart Mumford
Author-email: Joy Velasquez <joy.velasquez@cfa.harvard.edu>, Jonathan Slavin <jslavin@cfa.harvard.edu>, Nick Murpy <namurphy@cfa.harvard.edu>, Nabil Freij <nabil.freij@gmail.com>
License: BSD 2-Clause License
Project-URL: Changelog, https://xrtpy.readthedocs.io/en/stable/changelog/index.html
Project-URL: Documentation, https://xrtpy.readthedocs.io
Project-URL: Issues, https://github.com/HinodeXRT/xrtpy/issues
Project-URL: Repository, https://github.com/HinodeXRT/xrtpy
Keywords: Hinode,Solar Physics,x-ray,XRT
Classifier: Development Status :: 4 - Beta
Classifier: Intended Audience :: Science/Research
Classifier: License :: OSI Approved :: BSD License
Classifier: Operating System :: OS Independent
Classifier: Programming Language :: Python :: 3 :: Only
Classifier: Programming Language :: Python :: 3.11
Classifier: Programming Language :: Python :: 3.12
Classifier: Programming Language :: Python :: 3.13
Classifier: Topic :: Scientific/Engineering :: Astronomy
Classifier: Topic :: Scientific/Engineering :: Physics
Requires-Python: >=3.11
License-File: LICENSE
Requires-Dist: astropy>=6
Requires-Dist: matplotlib>=3.7
Requires-Dist: numpy>=1.24
Requires-Dist: scikit-image>=0.21
Requires-Dist: scipy>=1.11.1
Requires-Dist: sunpy[map]>=5.1
Provides-Extra: dev
Requires-Dist: nox>=2024.10.9; extra == "dev"
Provides-Extra: docs
Requires-Dist: astropy>=6; extra == "docs"
Requires-Dist: pydata-sphinx-theme>=0.15; extra == "docs"
Requires-Dist: setuptools>71.0.1; extra == "docs"
Requires-Dist: sphinx>=7.3; extra == "docs"
Requires-Dist: sphinx-automodapi>=0.17; extra == "docs"
Requires-Dist: sphinx-copybutton>=0.5.2; extra == "docs"
Requires-Dist: sphinx-gallery>=0.16; extra == "docs"
Requires-Dist: sphinx-hoverxref>=1.4; extra == "docs"
Requires-Dist: sphinx-issues>=4.1; extra == "docs"
Requires-Dist: sphinxcontrib-bibtex>=2.6.2; extra == "docs"
Requires-Dist: sphinxext-opengraph>=0.6; extra == "docs"
Requires-Dist: sunpy[map,net]>=5; extra == "docs"
Provides-Extra: tests
Requires-Dist: pytest>=8.3.1; extra == "tests"
Requires-Dist: pytest-astropy>=0.11; extra == "tests"
Requires-Dist: pytest-cov>=6; extra == "tests"
Requires-Dist: pytest-xdist>=3.6.1; extra == "tests"
Dynamic: license-file
